<?xml version="1.0" encoding="UTF-8"?>
<monster name="Slime" nameDescription="a slime" race="blood" experience="20" speed="180">
	<health now="6" max="6" />
	<!--- Level --><level min="7" max="10" />
	<look type="1384" corpse="37129" />
	<targetchange interval="4000" chance="10" />
	<flags>
		<flag summonable="0" />
		<flag attackable="1" />
		<flag hostile="1" />
		<flag illusionable="0" />
		<flag convinceable="0" />
		<flag pushable="0" />
		<flag canpushitems="0" />
		<flag canpushcreatures="0" />
		<flag targetdistance="1" />
		<flag staticattack="90" />
		<flag runonhealth="0" />
		<flag canwalkonenergy="0" />
		<flag canwalkonfire="0" />
	</flags>
	<attacks>
<attack name="melee" interval="2000" min="0" max="-25" />	
</attacks>
<defenses armor="1" defense="1" />

	<summons maxSummons="3">
		<summon name="Slime" interval="2000" chance="10" />
	</summons>
	<voices interval="5000" chance="10">
		<voice sentence="Blubb" />
	</voices>
	
	<loot>
		<item id="39162" countmax="2" chance="5000" /><!-- sell -->
		<item id="39077" countmax="2" chance="10000" /><!-- sell -->
	</loot>
</monster>
