<?xml version="1.0" encoding="UTF-8"?>
<monster name="Vampire" nameDescription="a vampire" race="blood" experience="15" speed="220" manacost="0">
	<health now="6" max="6" />
	<level min="390" max="400" />
	<look type="68" corpse="37129" />
	<targetchange interval="4000" chance="10" />
	<flags>
		<flag summonable="0" />
		<flag attackable="1" />
		<flag hostile="1" />
		<flag illusionable="1" />
		<flag convinceable="0" />
		<flag pushable="0" />
		<flag canpushitems="1" />
		<flag canpushcreatures="1" />
		<flag targetdistance="1" />
		<flag staticattack="90" />
		<flag runonhealth="30" />
	</flags>
	<attacks>
<attack name="melee" interval="2000" min="-2" max="-950" />		
		<attack name="speed" interval="2000" chance="15" range="1" target="1" speedchange="-400" duration="60000">
			<attribute key="areaEffect" value="redshimmer" />
		</attack>
	</attacks>
<defenses armor="1" defense="1" >

		<defense name="outfit" interval="4000" chance="10" monster="bat" duration="5000">
			<attribute key="areaEffect" value="groundshaker" />
		</defense>
		<defense name="speed" interval="2000" chance="15" speedchange="300" duration="3000">
			<attribute key="areaEffect" value="redshimmer" />
		</defense>
		<defense name="healing" interval="2000" chance="15" min="50" max="100" >
		<attribute key="areaEffect" value="bloodaura" />
		</defense>
	</defenses>
	
	
	<voices interval="2000" chance="7">
		<voice sentence="BLOOD!" yell="1" />
		<voice sentence="Let me kiss your neck" />
		<voice sentence="I smell warm blood!" />
		<voice sentence="I call you, my bats! Come!" />
	</voices>
	<loot>
	<item id="2363" countmax="1" chance="25000" />
	
		
		<item id="2534" chance="230" />					<!-- vampire shield -->
		<item id="2172" chance="220" />					<!-- bronze amulet -->

		<!-- t5 loot-->
		<item id="33430" chance="300" />
		<item id="33431" chance="300" />
		<item id="33432" chance="300" />
		<item id="34131" chance="300" />
		<item id="30220" chance="300" />
		<item id="33465" chance="300" />
		<item id="33165" chance="300" />
		<item id="36369" chance="300" />
		<item id="38578" chance="300" />
		<!-- t5 loot end-->

		
		<!-- trash-->
		<item id="39160" countmax="2" chance="1000" />
		<item id="39168" countmax="3" chance="500" />
		<item id="39167" countmax="1" chance="400" />
		<item id="39166" countmax="1" chance="400" />
		<item id="39147" countmax="1" chance="400" />
		<item id="39154" countmax="1" chance="200" />
		<!-- trash end-->

				<!-- rings-->
        <item id="38304" chance="350" /> <!-- Healing Touch -->
        <item id="38309" chance="350" /> <!-- Sorcerer's Circle -->
        <item id="38319" chance="350" /> <!-- Lifestealer's Band -->
        <item id="38305" chance="350" /> <!-- Mage's Seal -->
   

        <!-- amulets-->
        <item id="38241" chance="350" /> <!-- tank amulet -->
        <item id="38336" chance="350" /> <!-- magic amulet -->
		
	</loot>
</monster>
