<?xml version="1.0" encoding="ISO-8859-1"?>
<monster name="Banshee" nameDescription="a banshee" race="undead" experience="20" speed="200">
	<health now="6" max="6" />
	<level min="53" max="60" />
	<look type="2594" corpse="37129" />
	<targetchange interval="4000" chance="10" />
	<flags>
		<flag summonable="0" />
		<flag attackable="1" />
		<flag hostile="1" />
		<flag illusionable="0" />
		<flag convinceable="0" />
		<flag pushable="0" />
		<flag canpushitems="1" />
		<flag canpushcreatures="1" />
		<flag targetdistance="1" />
		<flag staticattack="70" />
		<flag runonhealth="0" />
		<flag canwalkonenergy="0" />
	</flags>
	<attacks>
<attack name="melee" interval="2000" min="0" max="-120" />		

	<attack name="death" interval="2000" chance="5" range="4" target="1" radius="2" min="-3" max="-180">
		<attribute key="areaEffect" value="effect435" />
	</attack>

	<attack name="lifedrain" interval="4000" chance="25" range="5" target="1" min="-30" max="-160">
    <attribute key="areaEffect" value="effect311"/>
</attack>
</attacks>
<defenses armor="1" defense="1" >

		<defense name="healing" interval="2000" chance="15" min="0" max="120">
			<attribute key="areaEffect" value="blueshimmer" />
		</defense>
	</defenses>
	
	
	<voices interval="5000" chance="10">
		<voice sentence="Dance for me your dance of death!" />
		<voice sentence="Let the music play!" />
		<voice sentence="I will mourn your death!" />
		<voice sentence="Are you ready to rock?" />
		<voice sentence="Feel my gentle kiss of death." />
		<voice sentence="That's what I call easy listening!" />
		<voice sentence="IIIIEEEeeeeeehhhHHHH!" yell="1" />
	</voices>
	<loot>
		
		<item name="silver amulet" chance="8700" />
		<item id="2175" chance="520" /><!-- spellbook -->
		<item id="32426" chance="900" /><!-- wands-->
		<item id="2189" chance="900" /><!-- wands-->
		<item id="32509" chance="500" /><!-- helmet-->
	
		<item id="38284"  chance="4500" /><!--kneck magic mana -->
		<item id="38279"  chance="4500" /><!--kneck magic  max mana + mana -->
		
		<item id="38333"  chance="4500" /><!--doom magic -->
	
		<item id="39145" countmax="1" chance="7500" /><!-- sell -->
	    <item id="39055" countmax="1" chance="6000" /><!-- sell -->
	    <item id="39070" countmax="2" chance="15500" /><!-- sell -->

		
		<item id="33441" chance="520" /><!-- spellbook -->
	</loot>
</monster>
